README.md
setup.py
pipx_python/__init__.py
pipx_python/main.py
pipx_python.egg-info/PKG-INFO
pipx_python.egg-info/SOURCES.txt
pipx_python.egg-info/dependency_links.txt
pipx_python.egg-info/entry_points.txt
pipx_python.egg-info/top_level.txt