Metadata-Version: 2.1
Name: pipx-python
Version: 1.0.0
Summary: Run the version of python corresponding to an executable installed with pipx
Home-page: https://github.com/talwrii/pipx-python
Author: talwrii
Author-email: talwrii@gmail.com
License: MIT
Keywords: pipx,python,virtualenv
